PyOverlayKit/__init__.py
PyOverlayKit/overlay.py
PyOverlayKit/windows_overlay.py
PyOverlayKit-0.3.0.dist-info/METADATA
PyOverlayKit-0.3.0.dist-info/WHEEL
PyOverlayKit-0.3.0.dist-info/top_level.txt
PyOverlayKit-0.3.0.dist-info/RECORD
