Metadata-Version: 2.1
Name: PyOverlayKit
Version: 0.3.0
Summary: Always-on-top overlays for PyQt and PySide, including when applications are full-screen.
Home-page: https://github.com/archiebhl/PyOverlayKit
Project-URL: Repository, https://github.com/archiebhl/PyOverlayKit
Classifier: Programming Language :: Python :: 3
Classifier: License :: OSI Approved :: MIT License
Classifier: Operating System :: OS Independent
Requires-Python: >=3.10.6
Requires-Dist: pyqtgraph
